funpicker/__init__.py
funpicker/config.py
funpicker/orderbook.py
funpicker/price.py
funpicker/query.py
funpicker/util/__init__.py
funpicker/util/converter.py
funpicker-0.2.2.dist-info/METADATA
funpicker-0.2.2.dist-info/RECORD
funpicker-0.2.2.dist-info/WHEEL
funpicker-0.2.2.dist-info/top_level.txt
