Metadata-Version: 2.1
Name: funpicker
Version: 0.2.2
Summary: A library to collect information for your trading bot. Use with `funtime` time series library
Home-page: UNKNOWN
Author: Kevin Hill
Author-email: kevin@funguana.com
License: UNKNOWN
Platform: UNKNOWN
Classifier: Programming Language :: Python :: 3
Classifier: License :: OSI Approved :: MIT License
Classifier: Operating System :: OS Independent
Requires-Dist: cryptocompare
Requires-Dist: ccxt
Requires-Dist: requests
